hop/__init__.py
hop/pipeline.py
hop/__pycache__/__init__.cpython-37.pyc
hop/__pycache__/__init__.cpython-38.pyc
hop/__pycache__/pipeline.cpython-37.pyc
hop/__pycache__/pipeline.cpython-38.pyc
hop/configuration/HECTOR_ClusterFieldsTest.R
hop/configuration/HECTOR_Config_v3.0.R
hop/configuration/HECTOR_Config_v3.2.R
hop/constants/HECTOR_CONSTANTS.yaml
hop/distortion_correction/HectorTranslationSoftware/Code/HectorConfigUtil
hop/distortion_correction/HectorTranslationSoftware/Code/HectorConfigUtil.cpp
hop/distortion_correction/HectorTranslationSoftware/Code/HectorConfigUtil.o
hop/distortion_correction/HectorTranslationSoftware/Code/HectorRaDecXY.cpp
hop/distortion_correction/HectorTranslationSoftware/Code/HectorRaDecXY.h
hop/distortion_correction/HectorTranslationSoftware/Code/HectorRaDecXY.o
hop/distortion_correction/HectorTranslationSoftware/Code/HectorSkyCheck.cpp
hop/distortion_correction/HectorTranslationSoftware/Code/HectorSkyCheck.h
hop/distortion_correction/HectorTranslationSoftware/Code/HectorStructures.h
hop/distortion_correction/HectorTranslationSoftware/Code/Makefile
hop/distortion_correction/HectorTranslationSoftware/Code/ProfitSkyCheck.cpp
hop/distortion_correction/HectorTranslationSoftware/Code/ProfitSkyCheck.h
hop/distortion_correction/HectorTranslationSoftware/Code/build.csh
hop/distortion_correction/HectorTranslationSoftware/Code/tdFdistortion0.sds
hop/distortion_correction/HectorTranslationSoftware/Packages/DramaErs/.mid
hop/distortion_correction/HectorTranslationSoftware/Packages/DramaErs/ChangeLog
hop/distortion_correction/HectorTranslationSoftware/Packages/DramaErs/Ers.h
hop/distortion_correction/HectorTranslationSoftware/Packages/DramaErs/Ers_Err.h
hop/distortion_correction/HectorTranslationSoftware/Packages/DramaErs/Ers_Err.msg
hop/distortion_correction/HectorTranslationSoftware/Packages/DramaErs/GNUmakefile.am
hop/distortion_correction/HectorTranslationSoftware/Packages/DramaErs/Makefile.standalone
Hector_Observations_Pipeline-0.2.6.dist-info/METADATA
Hector_Observations_Pipeline-0.2.6.dist-info/WHEEL
Hector_Observations_Pipeline-0.2.6.dist-info/top_level.txt
Hector_Observations_Pipeline-0.2.6.dist-info/RECORD
