Metadata-Version: 2.1
Name: Hector-Observations-Pipeline
Version: 0.2.6
Summary: Hector Galaxy Survey Observations pipeline
Home-page: https://github.com/samvaughan/Hector-Observations-Pipeline
Author: Sam Vaughan
Author-email: sam.vaughan@sydney.edu.au
License: GNU
Platform: UNKNOWN
Classifier: Programming Language :: Python :: 3
Classifier: Programming Language :: Python :: 3.8
